pointpy/__init__.py
pointpy/client.py
pointpy/oauth.py
pointpy-1.0.2.dist-info/LICENSE.txt
pointpy-1.0.2.dist-info/METADATA
pointpy-1.0.2.dist-info/WHEEL
pointpy-1.0.2.dist-info/top_level.txt
pointpy-1.0.2.dist-info/RECORD
