Metadata-Version: 2.1
Name: pointpy
Version: 1.0.2
Summary: point client
Home-page: UNKNOWN
Author: @gyran
Author-email: gustav.ahlberg@gmail.com
License: LICENSE.txt
Platform: UNKNOWN
Requires-Dist: requests (>=2.20.1)
